gefilte/__init__.py
gefilte/gefilte.py
gefilte-0.5.1.dist-info/LICENSE.txt
gefilte-0.5.1.dist-info/METADATA
gefilte-0.5.1.dist-info/WHEEL
gefilte-0.5.1.dist-info/top_level.txt
gefilte-0.5.1.dist-info/RECORD
