Metadata-Version: 2.1
Name: gefilte
Version: 0.5.1
Summary: Gefilte Fish GMail filter creator
Home-page: https://github.com/nedbat/gefilte
Author: Ned Batchelder
Author-email: ned@nedbatchelder.com
License: Apache
Platform: UNKNOWN
Classifier: Development Status :: 4 - Beta
Classifier: Intended Audience :: Developers
Classifier: License :: OSI Approved :: Apache Software License
Classifier: Natural Language :: English
Classifier: Programming Language :: Python :: 3
License-File: LICENSE.txt
